README.md
figure_parser/__init__.py
figure_parser/abcs.py
figure_parser/alter/__init__.py
figure_parser/alter/announcecment_parser.py
figure_parser/alter/product_parser.py
figure_parser/constants.py
figure_parser/exceptions.py
figure_parser/extension_class.py
figure_parser/factory.py
figure_parser/gsc/__init__.py
figure_parser/gsc/announcement_parser.py
figure_parser/gsc/locale/gsc_parse.yml
figure_parser/gsc/product_parser.py
figure_parser/gsc/shipment_parser.py
figure_parser/native/__init__.py
figure_parser/native/announcement_parser.py
figure_parser/native/product_parser.py
figure_parser/product.py
figure_parser/utils.py
figure_parser-0.1.0.dist-info/WHEEL
figure_parser-0.1.0.dist-info/METADATA
figure_parser-0.1.0.dist-info/RECORD
