Metadata-Version: 2.1
Name: figure-parser
Version: 0.1.0
Summary: Parser for figure
Home-page: https://github.com/FigureHook/figure_parser
License: MIT
Keywords: parser,figure
Author: Elton Chou
Author-email: plscd748@gmail.com
Requires-Python: >=3.9,<4.0
Classifier: Development Status :: 4 - Beta
Classifier: License :: OSI Approved :: MIT License
Classifier: Programming Language :: Python :: 3
Classifier: Programming Language :: Python :: 3 :: Only
Classifier: Programming Language :: Python :: 3.10
Classifier: Programming Language :: Python :: 3.9
Provides-Extra: docs
Requires-Dist: PyYAML (>=5.2,<6.0)
Requires-Dist: Sphinx (>=4.0.3,<5.0.0); extra == "docs"
Requires-Dist: aiohttp (>=3.7.4,<4.0.0)
Requires-Dist: beautifulsoup4 (>=4.9.3)
Requires-Dist: feedparser (>=6.0.8,<7.0.0)
Requires-Dist: furo (>=2021.7.5-beta.38,<2022.0.0); extra == "docs"
Requires-Dist: lxml (>=4.6.5)
Requires-Dist: pytz (>=2021.1,<2022.0)
Requires-Dist: requests (>=2.25.1)
Requires-Dist: sphinx-autodoc-typehints (>=1.12.0,<2.0.0); extra == "docs"
Requires-Dist: toml (>=0.10.2,<0.11.0)
Project-URL: Repository, https://github.com/FigureHook/figure_parser
